corpy/__init__.py
corpy/_magics.py
corpy/_version.py
corpy/py.typed
corpy/udpipe.py
corpy/util.py
corpy/vertical.py
corpy/vis.py
corpy/morphodita/__init__.py
corpy/morphodita/tagger.py
corpy/morphodita/tokenizer.py
corpy/phonetics/__init__.py
corpy/phonetics/cs.py
corpy/phonetics/exceptions.tsv
corpy/phonetics/phones.tsv
corpy/phonetics/substr2phones.tsv
corpy/phonetics/voicing_pairs.tsv
corpy/scripts/xc.py
corpy/scripts/zip_verticals.py
corpy-0.6.1.dist-info/METADATA
corpy-0.6.1.dist-info/WHEEL
corpy-0.6.1.dist-info/entry_points.txt
corpy-0.6.1.dist-info/top_level.txt
corpy-0.6.1.dist-info/RECORD
