Metadata-Version: 2.1
Name: corpy
Version: 0.6.1
Summary: Tools for processing language data.
Author-email: David Lukes <dafydd.lukes@gmail.com>
License: GPL-3.0-or-later
Project-URL: Documentation, https://corpy.rtfd.io
Project-URL: Issues, https://github.com/dlukes/corpy/issues
Project-URL: Source, https://github.com/dlukes/corpy
Keywords: corpus,linguistics,NLP
Classifier: Development Status :: 4 - Beta
Classifier: Intended Audience :: Developers
Classifier: Intended Audience :: Education
Classifier: Intended Audience :: Science/Research
Classifier: License :: OSI Approved :: GNU General Public License v3 or later (GPLv3+)
Classifier: Natural Language :: Czech
Classifier: Natural Language :: English
Classifier: Natural Language :: Slovak
Classifier: Operating System :: MacOS
Classifier: Operating System :: Microsoft :: Windows
Classifier: Operating System :: POSIX :: Linux
Classifier: Programming Language :: Python
Classifier: Programming Language :: Python :: 3.10
Classifier: Programming Language :: Python :: 3.11
Classifier: Programming Language :: Python :: Implementation :: CPython
Classifier: Programming Language :: Python :: Implementation :: PyPy
Classifier: Topic :: Education
Classifier: Topic :: Text Processing :: Linguistic
Classifier: Typing :: Typed
Requires-Python: >=3.10
Requires-Dist: regex
Requires-Dist: lxml (>=4.6.1)
Requires-Dist: wordcloud (>=1.8.1)
Requires-Dist: ufal.morphodita (>=1.10)
Requires-Dist: ufal.udpipe (>=1.2)
Requires-Dist: numpy (>=1.16)
Requires-Dist: click (>=7.0)
Provides-Extra: dev
Requires-Dist: ipython ; extra == 'dev'
Requires-Dist: ipdb ; extra == 'dev'
Requires-Dist: pytest ; extra == 'dev'
Requires-Dist: build ; extra == 'dev'
Requires-Dist: twine ; extra == 'dev'
Provides-Extra: doc
Requires-Dist: ipython ; extra == 'doc'
Requires-Dist: sphinx ; extra == 'doc'
Requires-Dist: furo ; extra == 'doc'
